[{"1": 0.8063963963963964, "2": 0.9568168168168169, "3": 0.9941741741741742, "4": 1.0}, {"1": {"date": [{"year": "2007", "month": "05", "day": "09"}, {"year": "2020", "month": "11", "day": "18"}, {"year": "2018", "month": "06", "day": "22"}, {"year": "2018", "month": "06", "day": "01"}, {"year": "2021", "month": "09", "day": "12"}, {"year": "2016", "month": "01", "day": "28"}, {"year": "2005", "month": "01", "day": "22"}, {"year": "2021", "month": "03", "day": "26"}, {"year": "2019", "month": "05", "day": "07"}, {"year": "2017", "month": "07", "day": "08"}, {"year": "2013", "month": "09", "day": "05"}, {"year": "2021", "month": "09", "day": "09"}, {"year": "2005", "month": "10", "day": "28"}, {"year": "2000", "month": "03", "day": "02"}, {"year": "2021", "month": "12", "day": "03"}, {"year": "2005", "month": "05", "day": "28"}, {"year": "2013", "month": "11", "day": "12"}, {"year": "2011", "month": "11", "day": "01"}, {"year": "2019", "month": "06", "day": "25"}, {"year": "2019", "month": "12", "day": "21"}, {"year": "2012", "month": "05", "day": "28"}, {"year": "2017", "month": "05", "day": "12"}, {"year": "2021", "month": "02", "day": "25"}, {"year": "2020", "month": "12", "day": "11"}, {"year": "2018", "month": "07", "day": "20"}, {"year": "2019", "month": "08", "day": "21"}, {"year": "2001", "month": "08", "day": "17"}, {"year": "2020", "month": "06", "day": "04"}, {"year": "2007", "month": "02", "day": "11"}, {"year": "2021", "month": "11", "day": "24"}, {"year": "2016", "month": "05", "day": "29"}, {"year": "2001", "month": "03", "day": "09"}, {"year": "2003", "month": "04", "day": "30"}, {"year": "2001", "month": "09", "day": "14"}, {"year": "2019", "month": "01", "day": "15"}, {"year": "2005", "month": "06", "day": "20"}, {"year": "2004", "month": "06", "day": "19"}, {"year": "2016", "month": "01", "day": "26"}, {"year": "2002", "month": "08", "day": "09"}, {"year": "2019", "month": "12", "day": "21"}, {"year": "2019", "month": "06", "day": "20"}, {"year": "2000", "month": "01", "day": "04"}, {"year": "2015", "month": "12", "day": "09"}, {"year": "2018", "month": "10", "day": "23"}, {"year": "2017", "month": "12", "day": "01"}, {"year": "2016", "month": "04", "day": "25"}, {"year": "2013", "month": "05", "day": "16"}, {"year": "2000", "month": "09", "day": "15"}, {"year": "2019", "month": "01", "day": "01"}, {"year": "2002", "month": "06", "day": "05"}, {"year": "2012", "month": "12", "day": "06"}, {"year": "2021", "month": "08", "day": "05"}, {"year": "2014", "month": "01", "day": "08"}, {"year": "2019", "month": "12", "day": "18"}, {"year": "2021", "month": "03", "day": "11"}, {"year": "2014", "month": "12", "day": "02"}, {"year": "2018", "month": "05", "day": "29"}, {"year": "2010", "month": "03", "day": "20"}, {"year": "2019", "month": "03", "day": "13"}, {"year": "2022", "month": "04", "day": "10"}, {"year": "2002", "month": "06", "day": "05"}, {"year": "2013", "month": "09", "day": "10"}, {"year": "2014", "month": "10", "day": "29"}, {"year": "2003", "month": "03", "day": "17"}, {"year": "2021", "month": "03", "day": "04"}, {"year": "2018", "month": "09", "day": "07"}, {"year": "2000", "month": "05", "day": "24"}, {"year": "2021", "month": "09", "day": "23"}, {"year": "2017", "month": "08", "day": "07"}, {"year": "2020", "month": "09", "day": "28"}, {"year": "2011", "month": "11", "day": "12"}, {"year": "2017", "month": "09", "day": "13"}, {"year": "2017", "month": "03", "day": "21"}, {"year": "2004", "month": "01", "day": "18"}, {"year": "2018", "month": "07", "day": "19"}, {"year": "2010", "month": "02", "day": "20"}, {"year": "2018", "month": "05", "day": "08"}, {"year": "2009", "month": "11", "day": "06"}, {"year": "2015", "month": "04", "day": "09"}, {"year": "2020", "month": "10", "day": "15"}, {"year": "2018", "month": "03", "day": "19"}, {"year": "2020", "month": "08", "day": "11"}, {"year": "2017", "month": "12", "day": "01"}, {"year": "2001", "month": "12", "day": "12"}, {"year": "2002", "month": "07", "day": "03"}, {"year": "2001", "month": "09", "day": "06"}, {"year": "2022", "month": "04", "day": "09"}, {"year": "2007", "month": "08", "day": "01"}, {"year": "2000", "month": "03", "day": "27"}, {"year": "2015", "month": "11", "day": "27"}, {"year": "2013", "month": "03", "day": "15"}, {"year": "2015", "month": "07", "day": "07"}, {"year": "2014", "month": "08", "day": "28"}, {"year": "2012", "month": "01", "day": "27"}, {"year": "2004", "month": "11", "day": "16"}, {"year": "2018", "month": "07", "day": "20"}, {"year": "2012", "month": "07", "day": "31"}, {"year": "2018", "month": "02", "day": "28"}, {"year": "2021", "month": "12", "day": "01"}, {"year": "2002", "month": "05", "day": "23"}], "topic": ["societe", "musiques", "idees", "politique", "le-monde-des-religions", "immigration-et-diversite", "archives", "afrique", "international", "international", "sport", "idees", "vous", "archives", "societe", "europe", "culture", "orientation-scolaire", "international", "culture", "a-la-une", "disparitions", "economie", "idees", "series-d-ete-2018-long-format", "festival", "archives", "societe", "societe", "societe", "disparitions", "archives", "archives", "archives", "international", "shoah-les-derniers-temoins-racontent", "archives", "biodiversite", "archives", "sport", "idees", "archives", "economie", "long-format", "culture", "afrique", "culture", "archives", "societe", "archives", "education", "series-d-ete", "planete", "actualite-medias", "culture", "pixels", "pixels", "economie", "afrique", "economie", "archives", "economie", "planete", "archives", "international", "syrie", "archives", "societe", "societe", "economie", "justice", "pixels", "europe", "archives", "idees", "idees", "societe", "idees", "sciences", "international", "ameriques", "mondephilatelique", "m-actu", "archives", "archives", "archives", "m-styles", "disparitions", "archives", "m-actu", "politique", "economie", "politique", "sports-de-combat", "idees", "m-actu", "societe", "police-justice", "m-le-mag", "archives"]}, "2": {"date": [{"year": "2000", "month": "08", "day": "30"}, {"year": "2008", "month": "07", "day": "15"}, {"year": "2008", "month": "01", "day": "01"}, {"year": "2001", "month": "04", "day": "24"}, {"year": "2016", "month": "11", "day": "14"}, {"year": "2018", "month": "10", "day": "26"}, {"year": "2017", "month": "12", "day": "28"}, {"year": "2021", "month": "09", "day": "01"}, {"year": "2019", "month": "08", "day": "23"}, {"year": "2003", "month": "10", "day": "31"}, {"year": "2012", "month": "05", "day": "28"}, {"year": "2017", "month": "11", "day": "07"}, {"year": "2016", "month": "08", "day": "26"}, {"year": "2001", "month": "11", "day": "13"}, {"year": "2001", "month": "05", "day": "08"}, {"year": "2007", "month": "08", "day": "18"}, {"year": "2016", "month": "04", "day": "27"}, {"year": "2013", "month": "09", "day": "23"}, {"year": "2020", "month": "12", "day": "06"}, {"year": "2018", "month": "08", "day": "15"}, {"year": "2017", "month": "02", "day": "06"}, {"year": "2012", "month": "03", "day": "14"}, {"year": "2013", "month": "02", "day": "16"}, {"year": "2002", "month": "02", "day": "24"}, {"year": "2016", "month": "02", "day": "29"}, {"year": "2015", "month": "09", "day": "26"}, {"year": "2012", "month": "10", "day": "12"}, {"year": "2012", "month": "02", "day": "27"}, {"year": "2004", "month": "06", "day": "19"}, {"year": "2012", "month": "01", "day": "11"}, {"year": "2001", "month": "11", "day": "13"}, {"year": "2019", "month": "02", "day": "18"}, {"year": "2018", "month": "09", "day": "15"}, {"year": "2017", "month": "06", "day": "30"}, {"year": "2012", "month": "01", "day": "20"}, {"year": "2010", "month": "10", "day": "15"}, {"year": "2017", "month": "01", "day": "04"}, {"year": "2019", "month": "09", "day": "28"}, {"year": "2020", "month": "08", "day": "16"}, {"year": "2018", "month": "08", "day": "26"}, {"year": "2014", "month": "04", "day": "15"}, {"year": "2001", "month": "12", "day": "07"}, {"year": "2018", "month": "06", "day": "22"}, {"year": "2015", "month": "08", "day": "30"}, {"year": "2013", "month": "12", "day": "13"}, {"year": "2018", "month": "06", "day": "18"}, {"year": "2001", "month": "03", "day": "16"}, {"year": "2020", "month": "06", "day": "30"}, {"year": "2003", "month": "12", "day": "06"}, {"year": "2002", "month": "12", "day": "20"}, {"year": "2011", "month": "07", "day": "01"}, {"year": "2017", "month": "01", "day": "04"}, {"year": "2018", "month": "01", "day": "08"}, {"year": "2015", "month": "11", "day": "26"}, {"year": "2010", "month": "09", "day": "28"}, {"year": "2006", "month": "01", "day": "27"}, {"year": "2021", "month": "03", "day": "02"}, {"year": "2003", "month": "06", "day": "02"}, {"year": "2002", "month": "03", "day": "02"}, {"year": "2019", "month": "09", "day": "02"}, {"year": "2001", "month": "09", "day": "29"}, {"year": "2019", "month": "12", "day": "13"}, {"year": "2007", "month": "10", "day": "29"}, {"year": "2011", "month": "09", "day": "09"}, {"year": "2020", "month": "06", "day": "23"}, {"year": "2020", "month": "11", "day": "23"}, {"year": "2000", "month": "05", "day": "11"}, {"year": "2001", "month": "04", "day": "11"}, {"year": "2002", "month": "05", "day": "08"}, {"year": "2005", "month": "01", "day": "03"}, {"year": "2005", "month": "10", "day": "13"}, {"year": "2022", "month": "03", "day": "21"}, {"year": "2014", "month": "03", "day": "24"}, {"year": "2018", "month": "06", "day": "14"}, {"year": "2021", "month": "07", "day": "23"}, {"year": "2013", "month": "11", "day": "29"}, {"year": "2004", "month": "10", "day": "08"}, {"year": "2017", "month": "07", "day": "22"}, {"year": "2020", "month": "03", "day": "02"}, {"year": "2019", "month": "07", "day": "30"}, {"year": "2006", "month": "02", "day": "15"}, {"year": "2012", "month": "05", "day": "07"}, {"year": "2017", "month": "03", "day": "09"}, {"year": "2016", "month": "05", "day": "26"}, {"year": "2018", "month": "07", "day": "03"}, {"year": "2014", "month": "07", "day": "08"}, {"year": "2018", "month": "04", "day": "27"}, {"year": "2001", "month": "10", "day": "16"}, {"year": "2012", "month": "07", "day": "20"}, {"year": "2005", "month": "01", "day": "29"}, {"year": "2016", "month": "05", "day": "23"}, {"year": "2014", "month": "05", "day": "26"}, {"year": "2004", "month": "05", "day": "03"}, {"year": "2016", "month": "03", "day": "10"}, {"year": "2002", "month": "01", "day": "19"}, {"year": "2017", "month": "03", "day": "03"}, {"year": "2011", "month": "12", "day": "14"}, {"year": "2018", "month": "09", "day": "24"}, {"year": "2007", "month": "04", "day": "26"}, {"year": "2017", "month": "08", "day": "10"}], "topic": ["archives", "voyage", "cinema", "archives", "syrie", "long-format", "cinema", "international", "musiques", "archives", "societe", "paradise-papers", "international", "archives", "archives", "sport", "idees", "idees", "culture", "les-decodeurs", "sciences", "sante", "a-la-une", "archives", "contes", "football", "sport", "justice", "archives", "societe", "archives", "societe", "economie", "culture", "proche-orient", "idees", "disparitions", "m-styles", "les-decodeurs", "disparitions", "idees", "archives", "international", "athletisme", "europe", "arts", "archives", "politique", "archives", "archives", "politique", "police-justice", "societe", "elections-regionales-2015", "voyage", "vous", "sante", "archives", "archives", "idees", "archives", "economie", "sport", "11-septembre", "societe", "economie", "archives", "archives", "archives", "archives", "a-la-une", "campus", "m-styles", "livres", "international", "planete", "archives", "la-republique-en-marche", "planete", "afrique", "planete", "election-presidentielle-2012", "election-presidentielle-2017", "climat", "afrique", "proche-orient", "m-actu", "archives", "sport", "archives", "economie", "tunisie", "archives", "musiques", "archives", "m-perso", "afrique", "europe", "societe", "livres"]}, "3": {"date": [{"year": "2022", "month": "01", "day": "24"}, {"year": "2007", "month": "04", "day": "22"}, {"year": "2020", "month": "07", "day": "02"}, {"year": "2006", "month": "06", "day": "22"}, {"year": "2007", "month": "06", "day": "05"}, {"year": "2017", "month": "05", "day": "12"}, {"year": "2013", "month": "09", "day": "06"}, {"year": "2019", "month": "03", "day": "26"}, {"year": "2001", "month": "10", "day": "24"}, {"year": "2005", "month": "12", "day": "24"}, {"year": "2003", "month": "10", "day": "24"}, {"year": "2020", "month": "05", "day": "26"}, {"year": "2003", "month": "09", "day": "01"}, {"year": "2020", "month": "06", "day": "12"}, {"year": "2013", "month": "07", "day": "11"}, {"year": "2002", "month": "01", "day": "21"}, {"year": "2017", "month": "02", "day": "23"}, {"year": "2013", "month": "07", "day": "28"}, {"year": "2000", "month": "09", "day": "05"}, {"year": "2000", "month": "06", "day": "30"}, {"year": "2013", "month": "06", "day": "11"}, {"year": "2021", "month": "04", "day": "18"}, {"year": "2001", "month": "08", "day": "23"}, {"year": "2000", "month": "03", "day": "27"}, {"year": "2010", "month": "07", "day": "19"}, {"year": "2017", "month": "04", "day": "20"}, {"year": "2015", "month": "10", "day": "22"}, {"year": "2006", "month": "09", "day": "25"}, {"year": "2021", "month": "12", "day": "17"}, {"year": "2018", "month": "11", "day": "07"}, {"year": "2001", "month": "03", "day": "13"}, {"year": "2017", "month": "03", "day": "07"}, {"year": "2001", "month": "07", "day": "10"}, {"year": "2017", "month": "04", "day": "03"}, {"year": "2017", "month": "10", "day": "13"}, {"year": "2001", "month": "10", "day": "05"}, {"year": "2021", "month": "10", "day": "01"}, {"year": "2008", "month": "02", "day": "21"}, {"year": "2002", "month": "03", "day": "01"}, {"year": "2018", "month": "05", "day": "28"}, {"year": "2011", "month": "11", "day": "07"}, {"year": "2004", "month": "09", "day": "29"}, {"year": "2018", "month": "06", "day": "22"}, {"year": "2013", "month": "02", "day": "05"}, {"year": "2009", "month": "01", "day": "30"}, {"year": "2000", "month": "09", "day": "02"}, {"year": "2010", "month": "11", "day": "18"}, {"year": "2013", "month": "10", "day": "03"}, {"year": "2009", "month": "12", "day": "07"}, {"year": "2000", "month": "11", "day": "26"}, {"year": "2002", "month": "08", "day": "31"}, {"year": "2017", "month": "02", "day": "04"}, {"year": "2000", "month": "07", "day": "30"}, {"year": "2000", "month": "05", "day": "28"}, {"year": "2002", "month": "10", "day": "30"}, {"year": "2016", "month": "07", "day": "26"}, {"year": "2002", "month": "05", "day": "28"}, {"year": "2017", "month": "05", "day": "15"}, {"year": "2005", "month": "05", "day": "13"}, {"year": "2017", "month": "06", "day": "30"}, {"year": "2019", "month": "08", "day": "26"}, {"year": "2004", "month": "02", "day": "23"}, {"year": "2020", "month": "08", "day": "19"}, {"year": "2020", "month": "07", "day": "30"}, {"year": "2019", "month": "06", "day": "30"}, {"year": "2003", "month": "08", "day": "07"}, {"year": "2021", "month": "08", "day": "20"}, {"year": "2002", "month": "11", "day": "29"}, {"year": "2016", "month": "11", "day": "18"}, {"year": "2001", "month": "10", "day": "06"}, {"year": "2009", "month": "01", "day": "21"}, {"year": "2004", "month": "04", "day": "29"}, {"year": "2012", "month": "05", "day": "07"}, {"year": "2000", "month": "10", "day": "31"}, {"year": "2000", "month": "10", "day": "01"}, {"year": "2017", "month": "02", "day": "27"}, {"year": "2019", "month": "02", "day": "08"}, {"year": "2002", "month": "07", "day": "03"}, {"year": "2002", "month": "05", "day": "29"}, {"year": "2005", "month": "04", "day": "12"}, {"year": "2019", "month": "07", "day": "19"}, {"year": "2007", "month": "06", "day": "10"}, {"year": "2001", "month": "08", "day": "03"}, {"year": "2005", "month": "10", "day": "11"}, {"year": "2003", "month": "10", "day": "23"}, {"year": "2015", "month": "02", "day": "21"}, {"year": "2016", "month": "03", "day": "17"}, {"year": "2012", "month": "04", "day": "14"}, {"year": "2012", "month": "01", "day": "28"}, {"year": "2022", "month": "01", "day": "21"}, {"year": "2018", "month": "06", "day": "07"}, {"year": "2014", "month": "09", "day": "29"}, {"year": "2010", "month": "04", "day": "21"}, {"year": "2006", "month": "09", "day": "20"}, {"year": "2000", "month": "11", "day": "18"}, {"year": "2010", "month": "11", "day": "23"}, {"year": "2019", "month": "12", "day": "14"}, {"year": "2013", "month": "08", "day": "01"}, {"year": "2008", "month": "01", "day": "19"}, {"year": "2014", "month": "06", "day": "02"}], "topic": ["economie", "societe", "m-styles", "ete-2007", "proche-orient", "argent", "m-actu", "idees", "archives", "vous", "archives", "m-styles", "archives", "m-le-mag", "economie", "archives", "economie", "natation", "archives", "archives", "international", "international", "archives", "archives", "a-la-une", "livres", "coupe-du-monde-rugby", "vous", "m-voyage", "idees", "archives", "argent", "archives", "economie", "proche-orient", "archives", "culture", "technologies", "archives", "smart-cities", "a-la-une", "culture", "m-actu", "asie-pacifique", "societe", "archives", "idees", "economie", "idees", "archives", "archives", "culture", "archives", "archives", "archives", "m-actu", "archives", "economie", "international", "tour-de-france", "politique", "archives", "international", "economie", "sport", "archives", "m-le-mag", "archives", "m-moyen-format", "archives", "ameriques", "archives", "import", "archives", "archives", "m-perso", "m-le-mag", "archives", "archives", "culture", "culture", "societe", "archives", "cinema", "archives", "enquetes", "campus", "culture", "international", "sport", "idees", "politique", "ameriques", "economie", "archives", "europe", "guides-d-achat", "a-la-une", "societe", "livres"]}, "4": {"date": [{"year": "2007", "month": "09", "day": "26"}, {"year": "2017", "month": "06", "day": "27"}, {"year": "2021", "month": "03", "day": "24"}, {"year": "2011", "month": "08", "day": "03"}, {"year": "2008", "month": "06", "day": "10"}, {"year": "2007", "month": "05", "day": "12"}, {"year": "2015", "month": "01", "day": "12"}, {"year": "2006", "month": "05", "day": "16"}, {"year": "2012", "month": "11", "day": "04"}, {"year": "2006", "month": "11", "day": "17"}, {"year": "2018", "month": "03", "day": "17"}, {"year": "2001", "month": "05", "day": "30"}, {"year": "2012", "month": "12", "day": "06"}, {"year": "2017", "month": "06", "day": "16"}, {"year": "2016", "month": "12", "day": "23"}, {"year": "2001", "month": "04", "day": "12"}, {"year": "2016", "month": "03", "day": "11"}, {"year": "2002", "month": "01", "day": "18"}, {"year": "2017", "month": "05", "day": "29"}, {"year": "2015", "month": "07", "day": "08"}, {"year": "2020", "month": "11", "day": "23"}, {"year": "2001", "month": "02", "day": "14"}, {"year": "2010", "month": "04", "day": "30"}, {"year": "2003", "month": "10", "day": "16"}, {"year": "2020", "month": "11", "day": "17"}, {"year": "2013", "month": "04", "day": "30"}, {"year": "2018", "month": "04", "day": "24"}, {"year": "2001", "month": "02", "day": "06"}, {"year": "2015", "month": "07", "day": "17"}, {"year": "2005", "month": "11", "day": "14"}, {"year": "2019", "month": "11", "day": "02"}, {"year": "2000", "month": "04", "day": "07"}, {"year": "2017", "month": "05", "day": "30"}, {"year": "2016", "month": "10", "day": "06"}, {"year": "2005", "month": "12", "day": "11"}, {"year": "2017", "month": "07", "day": "06"}, {"year": "2021", "month": "06", "day": "16"}, {"year": "2015", "month": "04", "day": "24"}, {"year": "2010", "month": "07", "day": "31"}, {"year": "2011", "month": "03", "day": "09"}, {"year": "2012", "month": "10", "day": "08"}, {"year": "2015", "month": "03", "day": "25"}, {"year": "2012", "month": "07", "day": "07"}, {"year": "2010", "month": "08", "day": "28"}, {"year": "2011", "month": "01", "day": "10"}, {"year": "2013", "month": "02", "day": "22"}, {"year": "2001", "month": "04", "day": "19"}, {"year": "2018", "month": "09", "day": "03"}, {"year": "2017", "month": "04", "day": "20"}, {"year": "2012", "month": "10", "day": "31"}, {"year": "2012", "month": "09", "day": "04"}, {"year": "2014", "month": "04", "day": "05"}, {"year": "2014", "month": "09", "day": "10"}, {"year": "2011", "month": "10", "day": "13"}, {"year": "2015", "month": "12", "day": "22"}, {"year": "2011", "month": "03", "day": "29"}, {"year": "2010", "month": "08", "day": "24"}, {"year": "2002", "month": "02", "day": "15"}, {"year": "2017", "month": "04", "day": "03"}, {"year": "2016", "month": "05", "day": "25"}, {"year": "2017", "month": "11", "day": "17"}, {"year": "2011", "month": "04", "day": "27"}, {"year": "2009", "month": "04", "day": "03"}, {"year": "2001", "month": "03", "day": "30"}, {"year": "2007", "month": "10", "day": "04"}, {"year": "2003", "month": "04", "day": "06"}, {"year": "2012", "month": "07", "day": "28"}, {"year": "2021", "month": "09", "day": "15"}, {"year": "2001", "month": "05", "day": "05"}, {"year": "2006", "month": "02", "day": "14"}, {"year": "2016", "month": "02", "day": "11"}, {"year": "2019", "month": "02", "day": "01"}, {"year": "2012", "month": "04", "day": "17"}, {"year": "2005", "month": "12", "day": "27"}, {"year": "2007", "month": "09", "day": "11"}, {"year": "2016", "month": "02", "day": "29"}, {"year": "2000", "month": "02", "day": "12"}, {"year": "2016", "month": "03", "day": "15"}, {"year": "2013", "month": "05", "day": "26"}, {"year": "2011", "month": "03", "day": "14"}, {"year": "2000", "month": "10", "day": "06"}, {"year": "2017", "month": "01", "day": "23"}, {"year": "2006", "month": "01", "day": "30"}, {"year": "2010", "month": "08", "day": "13"}, {"year": "2012", "month": "06", "day": "08"}, {"year": "2012", "month": "10", "day": "25"}, {"year": "2003", "month": "01", "day": "15"}, {"year": "2002", "month": "03", "day": "16"}, {"year": "2000", "month": "11", "day": "03"}, {"year": "2012", "month": "02", "day": "20"}, {"year": "2007", "month": "03", "day": "21"}, {"year": "2001", "month": "02", "day": "05"}, {"year": "2014", "month": "03", "day": "28"}, {"year": "2006", "month": "04", "day": "05"}, {"year": "2012", "month": "11", "day": "24"}, {"year": "2009", "month": "02", "day": "03"}, {"year": "2002", "month": "01", "day": "08"}, {"year": "2016", "month": "10", "day": "20"}, {"year": "2003", "month": "09", "day": "11"}, {"year": "2001", "month": "11", "day": "11"}], "topic": ["asie-pacifique", "police-justice", "culture", "europe", "euro-2008", "societe", "argent", "societe", "elections-americaines", "societe", "campus", "archives", "idees", "police-justice", "m-gens-portrait", "archives", "politique", "archives", "afrique", "partenaires", "idees", "archives", "a-la-une", "archives", "societe", "politique", "economie", "archives", "m-moyen-format", "societe", "m-perso", "archives", "vie-quotidienne", "idees", "sport", "afrique", "football", "politique", "asie-pacifique", "societe", "international", "elections-departementales-2015", "sport", "vous", "sport", "passeurdesciences", "archives", "politique", "planete", "politique", "economie", "politique", "culture", "economie", "cinema", "economie", "sport", "archives", "les-decodeurs", "les-decodeurs", "economie", "economie", "idees", "archives", "livres", "archives", "jeux-olympiques", "international", "archives", "international", "sciences", "m-le-mag", "economie", "idees", "mondephilatelique", "police-justice", "archives", "argent", "sport", "technologies", "archives", "asie-pacifique", "sport", "sport", "afrique", "societe", "archives", "archives", "archives", "planete", "societe", "archives", "afrique", "international", "archives", "la-crise-financiere", "archives", "elections-americaines", "archives", "archives"]}}]